activity_logger/__init__.py
activity_logger/cli.py
activity_logger/core.py
activity_logger-1.0.0.dist-info/licenses/LICENSE
activity_logger-1.0.0.dist-info/METADATA
activity_logger-1.0.0.dist-info/WHEEL
activity_logger-1.0.0.dist-info/entry_points.txt
activity_logger-1.0.0.dist-info/top_level.txt
activity_logger-1.0.0.dist-info/RECORD
