Metadata-Version: 2.4
Name: activity-logger
Version: 1.0.0
Summary: AI-powered activity logger that captures screenshots and analyzes user actions
Home-page: https://github.com/spakry/activity_logger
Author: Michael Kim
Author-email: Michael Kim <mjunyeopkim@gmail.com>
License: MIT License
Project-URL: Homepage, https://github.com/spakry/activity_logger
Project-URL: Repository, https://github.com/spakry/activity_logger
Project-URL: Issues, https://github.com/spakry/activity_logger/issues
Classifier: Development Status :: 4 - Beta
Classifier: Intended Audience :: End Users/Desktop
Classifier: License :: OSI Approved :: MIT License
Classifier: Operating System :: MacOS
Classifier: Programming Language :: Python :: 3
Classifier: Programming Language :: Python :: 3.8
Classifier: Programming Language :: Python :: 3.9
Classifier: Programming Language :: Python :: 3.10
Classifier: Programming Language :: Python :: 3.11
Classifier: Programming Language :: Python :: 3.12
Classifier: Topic :: Desktop Environment :: Screen Savers
Classifier: Topic :: System :: Monitoring
Requires-Python: >=3.8
License-File: LICENSE
Requires-Dist: mss>=9.0.1
Requires-Dist: pynput>=1.7.7
Requires-Dist: Pillow>=10.0.0
Requires-Dist: openai>=1.40.0
Requires-Dist: pyobjc-framework-Quartz>=10.0.0
Dynamic: author
Dynamic: home-page
Dynamic: license-file
Dynamic: requires-python
